sqlite_sqlean/__init__.py
sqlite_sqlean/crypto.dylib
sqlite_sqlean/define.dylib
sqlite_sqlean/fileio.dylib
sqlite_sqlean/fuzzy.dylib
sqlite_sqlean/ipaddr.dylib
sqlite_sqlean/json1.dylib
sqlite_sqlean/math.dylib
sqlite_sqlean/regexp.dylib
sqlite_sqlean/stats.dylib
sqlite_sqlean/text.dylib
sqlite_sqlean/unicode.dylib
sqlite_sqlean/uuid.dylib
sqlite_sqlean/vsv.dylib
sqlite_sqlean-0.1.dist-info/METADATA
sqlite_sqlean-0.1.dist-info/WHEEL
sqlite_sqlean-0.1.dist-info/top_level.txt
sqlite_sqlean-0.1.dist-info/RECORD
