Metadata-Version: 2.1
Name: sqlite-sqlean
Version: 0.1
Summary: Loadable sqlite extensions from sqlean
Home-page: http://github.com/karlb/sqlite-sqlean
License: UNKNOWN
Platform: UNKNOWN
Provides-Extra: test
Requires-Dist: pytest ; extra == 'test'
